google_maps_platform/__init__.py
google_maps_platform/config.py
google_maps_platform/places/__init__.py
google_maps_platform/places/config.py
google_maps_platform/places/field_masks.py
google_maps_platform/places/nearby_search.py
google_maps_platform/places/parameter_builders.py
google_maps_platform/places/place_details.py
google_maps_platform/places/shared_utils.py
google_maps_platform/places/text_search.py
google_maps_platform/places/utils.py
google_maps_platform-1.1.0.dist-info/licenses/LICENSE
google_maps_platform-1.1.0.dist-info/METADATA
google_maps_platform-1.1.0.dist-info/WHEEL
google_maps_platform-1.1.0.dist-info/top_level.txt
google_maps_platform-1.1.0.dist-info/RECORD
