Metadata-Version: 2.4
Name: Google-Maps-Platform
Version: 1.1.0
Summary: Unofficial Python library for Google Maps Platform APIs including Places API
Author-email: Chandan Gowda <chandangowdatk23@gmail.com>
License-Expression: MIT
Project-URL: Homepage, https://github.com/Chandangowdatk/Google-Maps-Platform
Project-URL: Repository, https://github.com/Chandangowdatk/Google-Maps-Platform
Project-URL: Documentation, https://github.com/Chandangowdatk/Google-Maps-Platform#readme
Project-URL: Bug Tracker, https://github.com/Chandangowdatk/Google-Maps-Platform/issues
Keywords: google maps platform,google places api,places,maps,client library,field masks,location search
Classifier: Development Status :: 4 - Beta
Classifier: Intended Audience :: Developers
Classifier: Operating System :: OS Independent
Classifier: Programming Language :: Python :: 3
Classifier: Programming Language :: Python :: 3.8
Classifier: Programming Language :: Python :: 3.9
Classifier: Programming Language :: Python :: 3.10
Classifier: Programming Language :: Python :: 3.11
Classifier: Programming Language :: Python :: 3.12
Classifier: Topic :: Software Development :: Libraries :: Python Modules
Classifier: Topic :: Internet :: WWW/HTTP :: Dynamic Content
Classifier: Topic :: Scientific/Engineering :: GIS
Requires-Python: >=3.8
License-File: LICENSE
Requires-Dist: requests>=2.31.0
Provides-Extra: dev
Requires-Dist: pytest>=7.0.0; extra == "dev"
Requires-Dist: pytest-cov>=4.0.0; extra == "dev"
Requires-Dist: black>=23.0.0; extra == "dev"
Requires-Dist: flake8>=6.0.0; extra == "dev"
Requires-Dist: mypy>=1.0.0; extra == "dev"
Provides-Extra: docs
Requires-Dist: sphinx>=6.0.0; extra == "docs"
Requires-Dist: sphinx-rtd-theme>=1.2.0; extra == "docs"
Dynamic: license-file
